Workbook

Sheet Сценарии
A1: Попутка — три сценария (посчитано этой моделью, переключатель на листе «Допущения», B2)
A3: Показатель | B3: Пессимист | C3: База | D3: Оптимист
A4: Средний чек, ₽ | B4: 1 100 | C4: 1 200 | D4: 1 300
A5: Курьер за заказ, ₽ | B5: 120 | C5: 100 | D5: 90
A6: Удержание активных м/м | B6: 65% | C6: 75% | D6: 85%
A7: CAC, ₽ | B7: 300 | C7: 200 | D7: 130
A8: Выручка с заказа, ₽ | B8: 184 | C8: 204 | D8: 219
A9: Маржа с заказа, ₽ | B9: 30 | C9: 69 | D9: 91
A10: LTV, ₽ | B10: 171 | C10: 829 | D10: 2 132
A11: LTV / CAC | B11: 0,6 | C11: 4,1 | D11: 16,4
A12: Активных к М6 | B12: 358 | C12: 674 | D12: 1 338
A13: Первый месяц в плюс | B13: нет за 12 мес | C13: М4 | D13: М3
A14: 500к вернулись | B14: нет за 12 мес | C14: М6 | D14: М3
... A16: Деньги к М12 | B16: 12 тыс. | C16: 1,31 млн | D16: 4,98 млн
A18: Стоп-правило: если на пилоте (нед. 5–6) в рейсе < 2 заказов или курьер > 120 ₽ за заказ — маркетинг не включаем, бюджет не сжигаем, меняем модель (слоты доставки, сужаем зону).
A19: Допущение: команда работает без зарплаты первые 12 мес (строка «Зарплата команды» в модели — можно задать).

Sheet Допущения
A1: Попутка — допущения фин. модели
A2: Сценарий (1 — пессимист, 2 — база, 3 — оптимист): | B2: 2
A3: Жёлтые ячейки можно менять — вся модель пересчитается.
A5: Параметр | B5: Пессимист | C5: База | D5: Оптимист | E5: АКТИВНЫЙ | F5: Комментарий
A6: Средний чек товаров, ₽ | B6: 1100 | C6: 1200 | D6: 1300 | E6: =CHOOSE($B$2,B6,C6,D6) | F6: корзина из 1–3 магазинов
A7: Доставка с клиента, ₽ | B7: 99 | C7: 99 | D7: 99 | E7: =CHOOSE($B$2,B7,C7,D7)
A8: Доля заказов с бесплатной доставкой | B8: 0.25 | C8: 0.15 | D8: 0.1 | E8: =CHOOSE($B$2,B8,C8,D8) | F8: попутные рейсы, промо
A9: Комиссия магазина | B9: 0.1 | C9: 0.1 | D9: 0.1 | E9: =CHOOSE($B$2,B9,C9,D9) | F9: агрегаторы берут 20–30%
A10: Эквайринг (от оплаты клиента) | B10: 0.025 | C10: 0.025 | D10: 0.025 | E10: =CHOOSE($B$2,B10,C10,D10) | F10: ЮKassa, агентская схема
A11: Курьер за заказ, ₽ | B11: 120 | C11: 100 | D11: 90 | E11: =CHOOSE($B$2,B11,C11,D11) | F11: рейс ~300 ₽ / заказов в рейсе
A12: ИИ + сервер за заказ, ₽ | B12: 5 | C12: 3 | D12: 3 | E12: =CHOOSE($B$2,B12,C12,D12) | F12: LLM-разбор, поиск по каталогу
A13: Заказов на активного в месяц | B13: 2 | C13: 3 | D13: 3.5 | E13: =CHOOSE($B$2,B13,C13,D13)
A14: Удержание активных месяц к месяцу | B14: 0.65 | C14: 0.75 | D14: 0.85 | E14: =CHOOSE($B$2,B14,C14,D14) | F14: связано с retention-7 > 25%
A15: CAC (маркетинг на 1 нового), ₽ | B15: 300 | C15: 200 | D15: 130 | E15: =CHOOSE($B$2,B15,C15,D15) | F15: QR в магазинах, паблики, листовки
A16: Рефералы: новые от активных в мес | B16: 0.03 | C16: 0.05 | D16: 0.08 | E16: =CHOOSE($B$2,B16,C16,D16) | F16: «приведи соседа»
A17: Заказов на 1 курьера в месяц | B17: 650 | C17: 650 | D17: 650 | E17: =CHOOSE($B$2,B17,C17,D17) | F17: ~25 в день × 26 дней
A18: Стартовый бюджет, ₽ | B18: 500000 | C18: 500000 | D18: 500000 | E18: =CHOOSE($B$2,B18,C18,D18) | F18: на 6 мес, доп. денег нет

Sheet Юнит-экономика
A1: Экономика одного заказа и клиента (активный сценарий)
A3: Выручка: доставка (с учётом бесплатных), ₽ | B3: ='Допущения'!$E$7*(1-'Допущения'!$E$8)
A4: Выручка: комиссия магазина, ₽ | B4: ='Допущения'!$E$6*'Допущения'!$E$9
A5: Выручка с заказа, ₽ | B5: =B3+B4
A6: Курьер, ₽ | B6: ='Допущения'!$E$11
A7: ИИ + сервер, ₽ | B7: ='Допущения'!$E$12
A8: Эквайринг, ₽ | B8: ='Допущения'!$E$10*('Допущения'!$E$6+B3)
A9: Переменные расходы на заказ, ₽ | B9: =B6+B7+B8
A10: Маржа с заказа, ₽ | B10: =B5-B9
A11: Маржа с клиента в месяц, ₽ | B11: =B10*'Допущения'!$E$13
A12: Срок жизни клиента, мес | B12: =1/(1-'Допущения'!$E$14)
A13: LTV (по марже), ₽ | B13: =B11*B12
A14: CAC, ₽ | B14: ='Допущения'!$E$15
A15: LTV / CAC | B15: =B13/B14
A16: Окупаемость CAC, мес | B16: =B14/B11

Sheet Фин модель (12 мес)
A1: Помесячная модель, ₽ (активный сценарий)
A2: Статья | B2: Итого | C2: М1 | D2: М2 | E2: М3 | F2: М4 | G2: М5 | H2: М6 | I2: М7 | J2: М8 | K2: М9 | L2: М10 | M2: М11 | N2: М12
A3: Маркетинг | B3: =SUM(C3:N3) | C3: 10000 | D3: 25000 | E3: 40000 | F3: 45000 | G3: 40000 | H3: 40000 | I3: 40000 | J3: 40000 | K3: 40000 | L3: 40000 | M3: 40000 | N3: 40000
A4: Разработка | B4: =SUM(C4:N4) | C4: 60000 | D4: 50000 | E4: 20000 | F4: 10000 | G4: 5000 | H4: 5000 | I4: 0 | J4: 0 | K4: 0 | L4: 0 | M4: 0 | N4: 0
A5: Гарантия курьерам | B5: =SUM(C5:N5) | C5: 20000 | D5: 20000 | E5: 20000 | F5: 0 | G5: 0 | H5: 0 | I5: 0 | J5: 0 | K5: 0 | L5: 0 | M5: 0 | N5: 0
A6: Сервер, API (фикс.) | B6: =SUM(C6:N6) | C6: 5000 | D6: 5000 | E6: 5000 | F6: 5000 | G6: 5000 | H6: 5000 | I6: 5000 | J6: 5000 | K6: 5000 | L6: 5000 | M6: 5000 | N6: 5000
A7: Зарплата команды | B7: =SUM(C7:N7) | C7: 0 | D7: 0 | E7: 0 | F7: 0 | G7: 0 | H7: 0 | I7: 0 | J7: 0 | K7: 0 | L7: 0 | M7: 0 | N7: 0
A8: Новые пользователи | B8: =SUM(C8:N8) | C8: =C3/'Допущения'!$E$15+'Допущения'!$E$16*0 | D8: =D3/'Допущения'!$E$15+'Допущения'!$E$16*C9 | E8: =E3/'Допущения'!$E$15+'Допущения'!$E$16*D9 | F8: =F3/'Допущения'!$E$15+'Допущения'!$E$16*E9 | G8: =G3/'Допущения'!$E$15+'Допущения'!$E$16*F9 | H8: =H3/'Допущения'!$E$15+'Допущения'!$E$16*G9 | I8: =I3/'Допущения'!$E$15+'Допущения'!$E$16*H9 | J8: =J3/'Допущения'!$E$15+'Допущения'!$E$16*I9 | K8: =K3/'Допущения'!$E$15+'Допущения'!$E$16*J9 | ... N8: =N3/'Допущения'!$E$15+'Допущения'!$E$16*M9
A9: Активные пользователи | B9: =N9 | C9: =0*'Допущения'!$E$14+C8 | D9: =C9*'Допущения'!$E$14+D8 | E9: =D9*'Допущения'!$E$14+E8 | F9: =E9*'Допущения'!$E$14+F8 | G9: =F9*'Допущения'!$E$14+G8 | H9: =G9*'Допущения'!$E$14+H8 | I9: =H9*'Допущения'!$E$14+I8 | J9: =I9*'Допущения'!$E$14+J8 | K9: =J9*'Допущения'!$E$14+K8 | ... N9: =M9*'Допущения'!$E$14+N8
A10: Заказы | B10: =SUM(C10:N10) | C10: =C9*'Допущения'!$E$13 | D10: =D9*'Допущения'!$E$13 | E10: =E9*'Допущения'!$E$13 | F10: =F9*'Допущения'!$E$13 | G10: =G9*'Допущения'!$E$13 | H10: =H9*'Допущения'!$E$13 | I10: =I9*'Допущения'!$E$13 | J10: =J9*'Допущения'!$E$13 | ... N10: =N9*'Допущения'!$E$13
A11: Оборот товаров (GMV) | B11: =SUM(C11:N11) | C11: =C10*'Допущения'!$E$6 | D11: =D10*'Допущения'!$E$6 | E11: =E10*'Допущения'!$E$6 | F11: =F10*'Допущения'!$E$6 | G11: =G10*'Допущения'!$E$6 | H11: =H10*'Допущения'!$E$6 | I11: =I10*'Допущения'!$E$6 | J11: =J10*'Допущения'!$E$6 | ... N11: =N10*'Допущения'!$E$6
A12: Выручка: доставка | B12: =SUM(C12:N12) | C12: =C10*'Юнит-экономика'!$B$3 | D12: =D10*'Юнит-экономика'!$B$3 | E12: =E10*'Юнит-экономика'!$B$3 | F12: =F10*'Юнит-экономика'!$B$3 | G12: =G10*'Юнит-экономика'!$B$3 | H12: =H10*'Юнит-экономика'!$B$3 | I12: =I10*'Юнит-экономика'!$B$3 | J12: =J10*'Юнит-экономика'!$B$3 | ... N12: =N10*'Юнит-экономика'!$B$3
A13: Выручка: комиссия | B13: =SUM(C13:N13) | C13: =C10*'Юнит-экономика'!$B$4 | D13: =D10*'Юнит-экономика'!$B$4 | E13: =E10*'Юнит-экономика'!$B$4 | F13: =F10*'Юнит-экономика'!$B$4 | G13: =G10*'Юнит-экономика'!$B$4 | H13: =H10*'Юнит-экономика'!$B$4 | I13: =I10*'Юнит-экономика'!$B$4 | J13: =J10*'Юнит-экономика'!$B$4 | ... N13: =N10*'Юнит-экономика'!$B$4
A14: Выручка итого | B14: =SUM(C14:N14) | C14: =C12+C13 | D14: =D12+D13 | E14: =E12+E13 | F14: =F12+F13 | G14: =G12+G13 | H14: =H12+H13 | I14: =I12+I13 | J14: =J12+J13 | ... N14: =N12+N13
A15: Курьеры | B15: =SUM(C15:N15) | C15: =C10*'Допущения'!$E$11 | D15: =D10*'Допущения'!$E$11 | E15: =E10*'Допущения'!$E$11 | F15: =F10*'Допущения'!$E$11 | G15: =G10*'Допущения'!$E$11 | H15: =H10*'Допущения'!$E$11 | I15: =I10*'Допущения'!$E$11 | J15: =J10*'Допущения'!$E$11 | ... N15: =N10*'Допущения'!$E$11
A16: ИИ + сервер (перем.) | B16: =SUM(C16:N16) | C16: =C10*'Допущения'!$E$12 | D16: =D10*'Допущения'!$E$12 | E16: =E10*'Допущения'!$E$12 | F16: =F10*'Допущения'!$E$12 | G16: =G10*'Допущения'!$E$12 | H16: =H10*'Допущения'!$E$12 | I16: =I10*'Допущения'!$E$12 | J16: =J10*'Допущения'!$E$12 | ... N16: =N10*'Допущения'!$E$12
A17: Эквайринг | B17: =SUM(C17:N17) | C17: =C10*'Юнит-экономика'!$B$8 | D17: =D10*'Юнит-экономика'!$B$8 | E17: =E10*'Юнит-экономика'!$B$8 | F17: =F10*'Юнит-экономика'!$B$8 | G17: =G10*'Юнит-экономика'!$B$8 | H17: =H10*'Юнит-экономика'!$B$8 | I17: =I10*'Юнит-экономика'!$B$8 | J17: =J10*'Юнит-экономика'!$B$8 | ... N17: =N10*'Юнит-экономика'!$B$8
A18: Маржа после перем. расходов | B18: =SUM(C18:N18) | C18: =C14-C15-C16-C17 | D18: =D14-D15-D16-D17 | E18: =E14-E15-E16-E17 | F18: =F14-F15-F16-F17 | G18: =G14-G15-G16-G17 | H18: =H14-H15-H16-H17 | I18: =I14-I15-I16-I17 | J18: =J14-J15-J16-J17 | ... N18: =N14-N15-N16-N17
A19: Постоянные расходы и инвестиции | B19: =SUM(C19:N19) | C19: =SUM(C3:C7) | D19: =SUM(D3:D7) | E19: =SUM(E3:E7) | F19: =SUM(F3:F7) | G19: =SUM(G3:G7) | H19: =SUM(H3:H7) | I19: =SUM(I3:I7) | J19: =SUM(J3:J7) | ... N19: =SUM(N3:N7)
A20: Результат месяца | B20: =SUM(C20:N20) | C20: =C18-C19 | D20: =D18-D19 | E20: =E18-E19 | F20: =F18-F19 | G20: =G18-G19 | H20: =H18-H19 | I20: =I18-I19 | J20: =J18-J19 | ... N20: =N18-N19
A21: Деньги на конец месяца | B21: =N21 | C21: ='Допущения'!$E$18+C20 | D21: =C21+D20 | E21: =D21+E20 | F21: =E21+F20 | G21: =F21+G20 | H21: =G21+H20 | I21: =H21+I20 | J21: =I21+J20 | K21: =J21+K20 | ... N21: =M21+N20
A22: Нужно курьеров | B22: =N22 | C22: =MAX(2,ROUNDUP(C10/'Допущения'!$E$17,0)) | D22: =MAX(2,ROUNDUP(D10/'Допущения'!$E$17,0)) | E22: =MAX(2,ROUNDUP(E10/'Допущения'!$E$17,0)) | F22: =MAX(2,ROUNDUP(F10/'Допущения'!$E$17,0)) | G22: =MAX(2,ROUNDUP(G10/'Допущения'!$E$17,0)) | H22: =MAX(2,ROUNDUP(H10/'Допущения'!$E$17,0)) | I22: =MAX(2,ROUNDUP(I10/'Допущения'!$E$17,0)) | J22: =MAX(2,ROUNDUP(J10/'Допущения'!$E$17,0)) | ... N22: =MAX(2,ROUNDUP(N10/'Допущения'!$E$17,0))
A24: Итоги
A25: Расходы бюджета за М1–М6 (маркетинг, разработка, гарантия, сервер) | B25: =SUM(C19:H19)
A26: Минимум денег на счёте за 12 мес | B26: =MIN(C21:N21)
A27: Деньги на конец М6 | B27: =H21
A28: Первый месяц с плюсом (результат > 0) | B28: =IFERROR(MATCH(TRUE,INDEX(C20:N20>0,0),0),"нет за 12 мес")
A29: Вложенные 500к вернулись (деньги ≥ старт), месяц | B29: =IFERROR(MATCH(TRUE,INDEX(C21:N21>='Допущения'!$E$18,0),0),"нет за 12 мес")
A30: Активных пользователей к М6 | B30: =H9
A31: Выручка за 12 мес | B31: =B14

Sheet Бюджет 500к
A1: Как тратим 500 тыс. за 6 месяцев
A2: Статья | B2: Сумма, ₽ | C2: Комментарий
A3: Разработка MVP | B3: =SUM('Фин модель (12 мес)'!C4:H4) | C3: боты клиента, магазина, курьера; ИИ-разбор; подключение прайсов
A4: Маркетинг | B4: =SUM('Фин модель (12 мес)'!C3:H3) | C4: QR в магазинах, паблики, листовки, первая доставка бесплатно
A5: Гарантия курьерам | B5: =SUM('Фин модель (12 мес)'!C5:H5) | C5: минимальный доход 2 курьерам на пилоте
A6: Сервер, API (фикс.) | B6: =SUM('Фин модель (12 мес)'!C6:H6) | C6: переменная часть ИИ (~3 ₽/заказ) покрывается выручкой
A7: Итого из бюджета | B7: =SUM(B3:B6)
A8: Резерв | B8: ='Допущения'!$E$18-B7 | C8: подушка на случай пессимистичного сценария
